aliyunsdkviapi_oxs_cross/__init__.py
aliyunsdkviapi_oxs_cross/request/__init__.py
aliyunsdkviapi_oxs_cross/request/v20200701/CreateSDKInstanceRequest.py
aliyunsdkviapi_oxs_cross/request/v20200701/GetSDKInstanceDebugInfoRequest.py
aliyunsdkviapi_oxs_cross/request/v20200701/QuerySDKInstancesRequest.py
aliyunsdkviapi_oxs_cross/request/v20200701/StartSDKInstanceProductionRequest.py
aliyunsdkviapi_oxs_cross/request/v20200701/__init__.py
aliyun_python_sdk_viapi_oxs_cross-1.0.0.dist-info/LICENSE
aliyun_python_sdk_viapi_oxs_cross-1.0.0.dist-info/METADATA
aliyun_python_sdk_viapi_oxs_cross-1.0.0.dist-info/WHEEL
aliyun_python_sdk_viapi_oxs_cross-1.0.0.dist-info/top_level.txt
aliyun_python_sdk_viapi_oxs_cross-1.0.0.dist-info/RECORD
